sharepoint_health/VERSION
sharepoint_health/__init__.py
sharepoint_health/__main__.py
sharepoint_health/plugin_check.py
sp_health-0.2.8.data/data/VERSION/VERSION
sp_health-0.2.8.dist-info/DESCRIPTION.rst
sp_health-0.2.8.dist-info/METADATA
sp_health-0.2.8.dist-info/RECORD
sp_health-0.2.8.dist-info/WHEEL
sp_health-0.2.8.dist-info/entry_points.txt
sp_health-0.2.8.dist-info/metadata.json
sp_health-0.2.8.dist-info/top_level.txt
