Metadata-Version: 2.0
Name: sp-health
Version: 0.2.8
Summary: Sharepoint health monitor nagios plugin
Home-page: https://github.com/pablodav/sharepoint_health_mon_plugin
Author: Pablo Estigarribia
Author-email: pablodav@gmail.com
License: MIT
Platform: UNKNOWN
Classifier: Development Status :: 5 - Production/Stable
Classifier: Intended Audience :: System Administrators
Classifier: License :: OSI Approved :: MIT License
Classifier: Programming Language :: Python :: 3
Classifier: Programming Language :: Python :: 3 :: Only
Classifier: Topic :: System :: Archiving :: Backup
Requires-Dist: SharePlum (==0.2.0)
Requires-Dist: requests (>=2.18.4)
Requires-Dist: rstcheck (>=3.1)
